git_upstream/__init__.py
git_upstream/errors.py
git_upstream/log.py
git_upstream/main.py
git_upstream/rebase_editor.py
git_upstream/commands/__init__.py
git_upstream/commands/drop.py
git_upstream/commands/help.py
git_upstream/commands/import.py
git_upstream/commands/supersede.py
git_upstream/lib/__init__.py
git_upstream/lib/drop.py
git_upstream/lib/importupstream.py
git_upstream/lib/note.py
git_upstream/lib/pygitcompat.py
git_upstream/lib/rebaseeditor.py
git_upstream/lib/searchers.py
git_upstream/lib/strategies.py
git_upstream/lib/supersede.py
git_upstream/lib/utils.py
git_upstream/resources/todo_epilogue_1_7_5.txt
git_upstream/resources/todo_epilogue_2_6_0.txt
git_upstream/tests/__init__.py
git_upstream/tests/base.py
git_upstream/tests/build-test-tree.py
git_upstream/tests/test_commands.py
git_upstream/tests/test_drop.py
git_upstream/tests/test_import.py
git_upstream/tests/test_log.py
git_upstream/tests/test_supersede.py
git_upstream/tests/commands/__init__.py
git_upstream/tests/commands/help/__init__.py
git_upstream/tests/commands/help/test_execute.py
git_upstream/tests/commands/import/__init__.py
git_upstream/tests/commands/import/test_conflict.py
git_upstream/tests/commands/import/test_failure.py
git_upstream/tests/commands/import/test_import.py
git_upstream/tests/commands/import/test_interactive.py
git_upstream/tests/commands/import/conflict_scenarios/basic.yaml
git_upstream/tests/commands/import/interactive_scenarios/basic.yaml
git_upstream/tests/commands/import/interactive_scenarios/import_no_merge.yaml
git_upstream/tests/commands/import/scenarios/basic.yaml
git_upstream/tests/commands/import/scenarios/basic_additional.yaml
git_upstream/tests/commands/import/scenarios/basic_additional_missed.yaml
git_upstream/tests/commands/import/scenarios/basic_use_alternative_refs.yaml
git_upstream/tests/commands/import/scenarios/import_everything_already_upstreamed.yaml
git_upstream-0.12.1.dist-info/DESCRIPTION.rst
git_upstream-0.12.1.dist-info/METADATA
git_upstream-0.12.1.dist-info/RECORD
git_upstream-0.12.1.dist-info/WHEEL
git_upstream-0.12.1.dist-info/entry_points.txt
git_upstream-0.12.1.dist-info/metadata.json
git_upstream-0.12.1.dist-info/pbr.json
git_upstream-0.12.1.dist-info/top_level.txt
