Metadata-Version: 2.0
Name: git-upstream
Version: 0.12.1
Summary: git tool to help manage upstream repositories
Home-page: https://pypi.python.org/pypi/git-upstream
Author: Darragh Bailey
Author-email: dbailey@hpe.com
License: Apache License (2.0)
Keywords: git upstream workflow
Platform: UNKNOWN
Requires-Dist: argcomplete
Requires-Dist: GitPython (>=1.0.1)
Requires-Dist: pbr (>=1.6)
Requires-Dist: six (>=1.9.0)
